binancema/__init__.py
binancema/coininfo.py
binancema/indicators.py
binance_ema-1.0.1.dist-info/LICENSE
binance_ema-1.0.1.dist-info/METADATA
binance_ema-1.0.1.dist-info/WHEEL
binance_ema-1.0.1.dist-info/RECORD
