Metadata-Version: 2.3
Name: binance-ema
Version: 1.0.1
Summary: Get crypto coin informations & calculate the custom or constant indicators. (WITH BINANCE API)
License: MIT License
Keywords: Binance,Public API,EMA,MACD,TRADE,Crypto,Coin,Indicators,BTC,ETH,USDT
Author: Emre MENTEŞE
Author-email: emrementese@gmail.com
Maintainer: Emre MENTEŞE
Maintainer-email: emrementese@gmail.com
Requires-Python: >=3.10
Classifier: Intended Audience :: Developers
Classifier: Intended Audience :: Financial and Insurance Industry
Classifier: License :: OSI Approved :: MIT License
Classifier: Operating System :: OS Independent
Classifier: Programming Language :: Python :: 3.10
Requires-Dist: binance-connector (==1.10.0)
Requires-Dist: pre-commit (>=4.0.1,<5.0.0)
Project-URL: Download, https://pypi.org/project/binance-ema/#files
Project-URL: Github, https://github.com/emrementese
Project-URL: Homepage, https://github.com/emrementese/binance-ema
Project-URL: Source, https://github.com/emrementese/binance-ema
